Binocular/configs/__init__.py
Binocular/configs/base_config.py
Binocular/datasets/nabirds/__init__.py
Binocular/datasets/nabirds/dataset.py
Binocular/datasets/nabirds/transforms.py
Binocular/datasets/nabirds/utils.py
Binocular/datasets/nabirds/data/nabirds.py
Binocular/examples/huggingface_inference.py
Binocular/examples/test_dataset.py
Binocular/examples/test_model.py
Binocular/models/__init__.py
Binocular/models/encoders.py
Binocular/models/inference.py
Binocular/models/linear_probe.py
Binocular/models/wrappers.py
Binocular/scripts/__init__.py
Binocular/scripts/add_class_names_to_checkpoint.py
Binocular/scripts/evaluate.py
Binocular/scripts/predict.py
Binocular/scripts/predict_hf.py
Binocular/scripts/preprocess_nabirds.py
Binocular/scripts/train.py
Binocular/scripts/upload_to_hf.py
Binocular/utils/__init__.py
Binocular/utils/checkpoint.py
Binocular/utils/hub.py
Binocular/utils/logger.py
Binocular/utils/metrics.py
Binocular/utils/optimizer.py
binocular_birds-0.1.0.dist-info/METADATA
binocular_birds-0.1.0.dist-info/WHEEL
binocular_birds-0.1.0.dist-info/entry_points.txt
binocular_birds-0.1.0.dist-info/top_level.txt
binocular_birds-0.1.0.dist-info/RECORD
