Metadata-Version: 2.4
Name: binocular-birds
Version: 0.1.0
Summary: A bird species classifier
Author-email: jiujiuche <jiujiuche@gmail.com>
License-Expression: MIT
Project-URL: Homepage, https://github.com/JiuJiuChe/Binocular
Project-URL: Bug Tracker, https://github.com/JiuJiuChe/Binocular/issues
Classifier: Programming Language :: Python :: 3
Classifier: Operating System :: OS Independent
Requires-Python: >=3.8
Requires-Dist: torch
Requires-Dist: torchvision
Requires-Dist: matplotlib
Requires-Dist: networkx
Requires-Dist: tqdm
Requires-Dist: pyyaml
Requires-Dist: tensorboard
Requires-Dist: huggingface-hub
Requires-Dist: Pillow
